asynclib/__init__.py
asynclib/afunctools.py
asynclib-0.0.0.dist-info/DESCRIPTION.rst
asynclib-0.0.0.dist-info/METADATA
asynclib-0.0.0.dist-info/RECORD
asynclib-0.0.0.dist-info/WHEEL
asynclib-0.0.0.dist-info/metadata.json
asynclib-0.0.0.dist-info/top_level.txt
