Metadata-Version: 2.0
Name: asynclib
Version: 0.0.0
Summary: Utlity library for working with async python, including some stdlib replacements to be compatible with native coroutines.
Home-page: https://github.com/wickedasp/asynclib
Author: Matt Rasband, Nick Humrich
Author-email: matt.rasband@gmail.com
License: Apache-2.0
Download-URL: https://github.com/wickedasp/asynclib/releases/v0.0.1.tar.gz
Keywords: asyncio
Platform: UNKNOWN
Classifier: Programming Language :: Python :: 3.5
Classifier: Programming Language :: Python :: 3.6
Classifier: Programming Language :: Python :: 3 :: Only
Classifier: License :: OSI Approved :: Apache Software License
Classifier: Intended Audience :: Developers
Classifier: Development Status :: 2 - Pre-Alpha
Classifier: Topic :: Software Development
